{
  "accountAssociation": {
    "header": "",
    "payload": "",
    "signature": ""
  },
  "baseBuilder": {
    "allowedAddresses": [
      "0x083fc8c8ccC3c2628fea6918cfE5c8E31239D251"
    ]
  },
  "miniapp": {
    "version": "1",
    "name": "Skadi",
    "noindex": true,
    "subtitle": "The only crypto tool you need",
    "description": "AI assistant for crypto",
    "screenshotUrls": [
      "https://waitlist-mini-app-gules.vercel.app/screenshot-portrait.png"
    ],
    "iconUrl": "https://waitlist-mini-app-gules.vercel.app/blue-icon.png",
    "splashImageUrl": "https://waitlist-mini-app-gules.vercel.app/blue-hero.png",
    "splashBackgroundColor": "#000000",
    "homeUrl": "https://waitlist-mini-app-gules.vercel.app",
    "webhookUrl": "https://waitlist-mini-app-gules.vercel.app/api/webhook",
    "primaryCategory": "social",
    "tags": [
      "marketing",
      "ads",
      "quickstart",
      "waitlist",
      "nfts"
    ],
    "heroImageUrl": "https://waitlist-mini-app-gules.vercel.app/blue-hero.png",
    "ogImageUrl": "https://waitlist-mini-app-gules.vercel.app/blue-hero.png"
  }
}